{"1st/BAS103":{"pdf-notes":true,"aktu-pyq":true,"cae":true,"handwritten":true,"quantum":true,"question-bank":true},"1st/BAS101":{"pdf-notes":true,"aktu-pyq":true,"cae":true,"handwritten":true,"quantum":true,"question-bank":true},"1st/BAS102":{"pdf-notes":true,"aktu-pyq":true,"cae":true,"handwritten":true,"quantum":true,"question-bank":true},"1st/BCS101":{"pdf-notes":true,"aktu-pyq":true,"cae":true,"handwritten":true,"quantum":true,"question-bank":true},"1st/BEE101":{"pdf-notes":true,"aktu-pyq":true,"cae":true,"handwritten":true,"quantum":true,"question-bank":true},"1st/BME101":{"pdf-notes":true,"aktu-pyq":true,"cae":true,"handwritten":true,"quantum":true,"question-bank":true},"1st/BAS104":{"handwritten":true,"aktu-pyq":true,"quantum":true},"1st/BAS105":{"pdf-notes":true,"aktu-pyq":true,"cae":true,"handwritten":true,"quantum":true,"question-bank":true},"1st/BEC101":{"pdf-notes":true,"aktu-pyq":true,"cae":true,"handwritten":true,"quantum":true,"question-bank":true},"2nd/BAS301":{"pdf-notes":true,"aktu-pyq":true,"cae":true,"handwritten":true,"quantum":true,"question-bank":true},"2nd/BAS303":{"pdf-notes":true,"aktu-pyq":true,"cae":true,"handwritten":true,"quantum":true,"question-bank":true},"2nd/BCC301":{"pdf-notes":true,"aktu-pyq":true,"cae":true,"handwritten":true,"quantum":true,"question-bank":true},"2nd/BCC302":{"pdf-notes":true,"aktu-pyq":true,"cae":true,"handwritten":true,"quantum":true,"question-bank":true},"2nd/BCS301":{"pdf-notes":true,"aktu-pyq":true,"cae":true,"handwritten":true,"quantum":true,"question-bank":true},"2nd/BCS302":{"pdf-notes":true,"aktu-pyq":true,"cae":true,"handwritten":true,"quantum":true,"question-bank":true},"2nd/BCS303":{"pdf-notes":true,"aktu-pyq":true,"cae":true,"handwritten":true,"quantum":true,"question-bank":true},"2nd/BOE307":{"pdf-notes":true,"aktu-pyq":true,"cae":true,"handwritten":true,"quantum":true,"question-bank":true},"2nd/BOE310":{"pdf-notes":true,"aktu-pyq":true,"cae":true,"handwritten":true,"quantum":true,"question-bank":true},"2nd/BVE301":{"pdf-notes":true,"aktu-pyq":true,"cae":true,"handwritten":true,"quantum":true,"question-bank":true},"2nd/BAS401":{"pdf-notes":true,"aktu-pyq":true,"cae":true,"handwritten":true,"quantum":true,"question-bank":true},"2nd/BAS403":{"pdf-notes":true,"aktu-pyq":true,"cae":true,"handwritten":true,"quantum":true,"question-bank":true},"2nd/BCC401":{"pdf-notes":true,"aktu-pyq":true,"cae":true,"handwritten":true,"quantum":true,"question-bank":true},"2nd/BCC402":{"pdf-notes":true,"aktu-pyq":true,"cae":true,"handwritten":true,"quantum":true,"question-bank":true},"2nd/BCE401":{"pdf-notes":true,"aktu-pyq":true,"cae":true,"handwritten":true,"quantum":true,"question-bank":true},"2nd/BCE403":{"pdf-notes":true,"aktu-pyq":true,"cae":true,"handwritten":true,"quantum":true,"question-bank":true},"2nd/BCS401":{"pdf-notes":true,"aktu-pyq":true,"cae":true,"handwritten":true,"quantum":true,"question-bank":true},"2nd/BCS402":{"pdf-notes":true,"aktu-pyq":true,"cae":true,"handwritten":true,"quantum":true,"question-bank":true},"2nd/BCS403":{"pdf-notes":true,"aktu-pyq":true,"cae":true,"handwritten":true,"quantum":true,"question-bank":true},"2nd/BEC401":{"pdf-notes":true,"aktu-pyq":true,"cae":true,"handwritten":true,"quantum":true,"question-bank":true},"2nd/BEC402":{"pdf-notes":true,"aktu-pyq":true,"cae":true,"handwritten":true,"quantum":true,"question-bank":true},"2nd/BEC403":{"pdf-notes":true,"aktu-pyq":true,"cae":true,"handwritten":true,"quantum":true,"question-bank":true},"2nd/BEE401":{"pdf-notes":true,"aktu-pyq":true,"cae":true,"handwritten":true,"quantum":true,"question-bank":true},"2nd/BEE402":{"pdf-notes":true,"aktu-pyq":true,"cae":true,"handwritten":true,"quantum":true,"question-bank":true},"2nd/BEE403":{"pdf-notes":true,"aktu-pyq":true,"cae":true,"handwritten":true,"quantum":true,"question-bank":true},"2nd/BME401":{"pdf-notes":true,"aktu-pyq":true,"cae":true,"handwritten":true,"quantum":true,"question-bank":true},"2nd/BME402":{"pdf-notes":true,"aktu-pyq":true,"cae":true,"handwritten":true,"quantum":true,"question-bank":true},"2nd/BME403":{"pdf-notes":true,"aktu-pyq":true,"cae":true,"handwritten":true,"quantum":true,"question-bank":true},"2nd/BOE401":{"pdf-notes":true,"aktu-pyq":true,"cae":true,"handwritten":true,"quantum":true,"question-bank":true},"2nd/BOE402":{"pdf-notes":true,"aktu-pyq":true,"cae":true,"handwritten":true,"quantum":true,"question-bank":true},"2nd/BOE403":{"pdf-notes":true,"aktu-pyq":true,"cae":true,"handwritten":true,"quantum":true,"question-bank":true},"2nd/BOE404":{"pdf-notes":true,"aktu-pyq":true,"cae":true,"handwritten":true,"quantum":true,"question-bank":true},"2nd/BOE405":{"pdf-notes":true,"aktu-pyq":true,"cae":true,"handwritten":true,"quantum":true,"question-bank":true},"2nd/BOE406":{"pdf-notes":true,"aktu-pyq":true,"cae":true,"handwritten":true,"quantum":true,"question-bank":true},"2nd/BOE407":{"pdf-notes":true,"aktu-pyq":true,"cae":true,"handwritten":true,"quantum":true,"question-bank":true},"2nd/BOE408":{"pdf-notes":true,"aktu-pyq":true,"cae":true,"handwritten":true,"quantum":true,"question-bank":true},"2nd/BOE409":{"pdf-notes":true,"aktu-pyq":true,"cae":true,"handwritten":true,"quantum":true,"question-bank":true},"2nd/BOE410":{"pdf-notes":true,"aktu-pyq":true,"cae":true,"handwritten":true,"quantum":true,"question-bank":true},"2nd/BOE411":{"pdf-notes":true,"aktu-pyq":true,"cae":true,"handwritten":true,"quantum":true,"question-bank":true},"2nd/BOE412":{"pdf-notes":true,"aktu-pyq":true,"cae":true,"handwritten":true,"quantum":true,"question-bank":true},"2nd/BOE413":{"pdf-notes":true,"aktu-pyq":true,"cae":true,"handwritten":true,"quantum":true,"question-bank":true},"2nd/BOE414":{"pdf-notes":true,"aktu-pyq":true,"cae":true,"handwritten":true,"quantum":true,"question-bank":true},"2nd/BVE401":{"pdf-notes":true,"aktu-pyq":true,"cae":true,"handwritten":true,"quantum":true,"question-bank":true},"3rd/BCAI051":{"pdf-notes":true,"aktu-pyq":true,"cae":true,"handwritten":true,"quantum":true,"question-bank":true},"3rd/BCAM051":{"pdf-notes":true,"aktu-pyq":true,"cae":true,"handwritten":true,"quantum":true,"question-bank":true},"3rd/BCDS051":{"pdf-notes":true,"aktu-pyq":true,"cae":true,"handwritten":true,"quantum":true,"question-bank":true},"3rd/BCS052":{"pdf-notes":true,"aktu-pyq":true,"cae":true,"handwritten":true,"quantum":true,"question-bank":true},"3rd/BCS054":{"pdf-notes":true,"aktu-pyq":true,"cae":true,"handwritten":true,"quantum":true,"question-bank":true},"3rd/BCS055":{"pdf-notes":true,"aktu-pyq":true,"cae":true,"handwritten":true,"quantum":true,"question-bank":true},"3rd/BCS056":{"pdf-notes":true,"aktu-pyq":true,"cae":true,"handwritten":true,"quantum":true,"question-bank":true},"3rd/BCS057":{"pdf-notes":true,"aktu-pyq":true,"cae":true,"handwritten":true,"quantum":true,"question-bank":true},"3rd/BCS501":{"pdf-notes":true,"aktu-pyq":true,"cae":true,"handwritten":true,"quantum":true,"question-bank":true},"3rd/BCS502":{"pdf-notes":true,"aktu-pyq":true,"cae":true,"handwritten":true,"quantum":true,"question-bank":true},"3rd/BCS503":{"pdf-notes":true,"aktu-pyq":true,"cae":true,"handwritten":true,"quantum":true,"question-bank":true},"3rd/BEC503":{"pdf-notes":true,"aktu-pyq":true,"cae":true,"handwritten":true,"quantum":true,"question-bank":true},"3rd/BEE057":{"pdf-notes":true,"aktu-pyq":true,"cae":true,"handwritten":true,"quantum":true,"question-bank":true},"3rd/BEE501":{"pdf-notes":true,"aktu-pyq":true,"cae":true,"handwritten":true,"quantum":true,"question-bank":true},"3rd/BEE502":{"pdf-notes":true,"aktu-pyq":true,"cae":true,"handwritten":true,"quantum":true,"question-bank":true},"3rd/BME501":{"pdf-notes":true,"aktu-pyq":true,"cae":true,"handwritten":true,"quantum":true,"question-bank":true},"3rd/BME502":{"pdf-notes":true,"aktu-pyq":true,"cae":true,"handwritten":true,"quantum":true,"question-bank":true},"3rd/BME503":{"pdf-notes":true,"aktu-pyq":true,"cae":true,"handwritten":true,"quantum":true,"question-bank":true},"3rd/BNC501":{"pdf-notes":true,"aktu-pyq":true,"cae":true,"handwritten":true,"quantum":true,"question-bank":true},"3rd/BNC502":{"pdf-notes":true,"aktu-pyq":true,"cae":true,"handwritten":true,"quantum":true,"question-bank":true},"3rd/BCD061":{"pdf-notes":true,"aktu-pyq":true,"cae":true,"handwritten":true,"quantum":true,"question-bank":true},"3rd/BCDS062":{"pdf-notes":true,"aktu-pyq":true,"cae":true,"handwritten":true,"quantum":true,"question-bank":true},"3rd/BCDS601":{"pdf-notes":true,"aktu-pyq":true,"cae":true,"handwritten":true,"quantum":true,"question-bank":true},"3rd/BCS064":{"pdf-notes":true,"aktu-pyq":true,"cae":true,"handwritten":true,"quantum":true,"question-bank":true},"3rd/BCS601":{"pdf-notes":true,"aktu-pyq":true,"cae":true,"handwritten":true,"quantum":true,"question-bank":true},"3rd/BCS602":{"pdf-notes":true,"aktu-pyq":true,"cae":true,"handwritten":true,"quantum":true,"question-bank":true},"3rd/BCS603":{"pdf-notes":true,"aktu-pyq":true,"cae":true,"handwritten":true,"quantum":true,"question-bank":true},"3rd/BOE064":{"pdf-notes":true,"aktu-pyq":true,"cae":true,"handwritten":true,"quantum":true,"question-bank":true},"3rd/BOE068":{"pdf-notes":true,"aktu-pyq":true,"cae":true,"handwritten":true,"quantum":true,"question-bank":true},"4th/KCE079":{"pdf-notes":true,"aktu-pyq":true,"cae":true,"handwritten":true,"quantum":true,"question-bank":true},"4th/KCS071":{"pdf-notes":true,"aktu-pyq":true,"cae":true,"handwritten":true,"quantum":true,"question-bank":true},"4th/KCS072":{"pdf-notes":true,"aktu-pyq":true,"cae":true,"handwritten":true,"quantum":true,"question-bank":true},"4th/KCS073":{"pdf-notes":true,"aktu-pyq":true,"cae":true,"handwritten":true,"quantum":true,"question-bank":true},"4th/KCS074":{"pdf-notes":true,"aktu-pyq":true,"cae":true,"handwritten":true,"quantum":true,"question-bank":true},"4th/KCS075":{"pdf-notes":true,"aktu-pyq":true,"cae":true,"handwritten":true,"quantum":true,"question-bank":true},"4th/KCS078":{"pdf-notes":true,"aktu-pyq":true,"cae":true,"handwritten":true,"quantum":true,"question-bank":true},"4th/KCS079":{"pdf-notes":true,"aktu-pyq":true,"cae":true,"handwritten":true,"quantum":true,"question-bank":true},"4th/KCS710":{"pdf-notes":true,"aktu-pyq":true,"cae":true,"handwritten":true,"quantum":true,"question-bank":true},"4th/KCS711":{"pdf-notes":true,"aktu-pyq":true,"cae":true,"handwritten":true,"quantum":true,"question-bank":true},"4th/KCS712":{"pdf-notes":true,"aktu-pyq":true,"cae":true,"handwritten":true,"quantum":true,"question-bank":true},"4th/KCS713":{"pdf-notes":true,"aktu-pyq":true,"cae":true,"handwritten":true,"quantum":true,"question-bank":true},"4th/KCS714":{"pdf-notes":true,"aktu-pyq":true,"cae":true,"handwritten":true,"quantum":true,"question-bank":true},"4th/KDS071":{"pdf-notes":true,"aktu-pyq":true,"cae":true,"handwritten":true,"quantum":true,"question-bank":true},"4th/KDS073":{"pdf-notes":true,"aktu-pyq":true,"cae":true,"handwritten":true,"quantum":true,"question-bank":true},"4th/KDS078":{"pdf-notes":true,"aktu-pyq":true,"cae":true,"handwritten":true,"quantum":true,"question-bank":true},"4th/KDS079":{"pdf-notes":true,"aktu-pyq":true,"cae":true,"handwritten":true,"quantum":true,"question-bank":true},"4th/KEC071":{"pdf-notes":true,"aktu-pyq":true,"cae":true,"handwritten":true,"quantum":true,"question-bank":true},"4th/KEC072":{"pdf-notes":true,"aktu-pyq":true,"cae":true,"handwritten":true,"quantum":true,"question-bank":true},"4th/KEC073":{"pdf-notes":true,"aktu-pyq":true,"cae":true,"handwritten":true,"quantum":true,"question-bank":true},"4th/KEC074":{"pdf-notes":true,"aktu-pyq":true,"cae":true,"handwritten":true,"quantum":true,"question-bank":true},"4th/KEC075":{"pdf-notes":true,"aktu-pyq":true,"cae":true,"handwritten":true,"quantum":true,"question-bank":true},"4th/KEC076":{"pdf-notes":true,"aktu-pyq":true,"cae":true,"handwritten":true,"quantum":true,"question-bank":true},"4th/KEC077":{"pdf-notes":true,"aktu-pyq":true,"cae":true,"handwritten":true,"quantum":true,"question-bank":true},"4th/KEC078":{"pdf-notes":true,"aktu-pyq":true,"cae":true,"handwritten":true,"quantum":true,"question-bank":true},"4th/KEE070":{"pdf-notes":true,"aktu-pyq":true,"cae":true,"handwritten":true,"quantum":true,"question-bank":true},"4th/KEE071":{"pdf-notes":true,"aktu-pyq":true,"cae":true,"handwritten":true,"quantum":true,"question-bank":true},"4th/KEE072":{"pdf-notes":true,"aktu-pyq":true,"cae":true,"handwritten":true,"quantum":true,"question-bank":true},"4th/KEE073":{"pdf-notes":true,"aktu-pyq":true,"cae":true,"handwritten":true,"quantum":true,"question-bank":true},"4th/KEE074":{"pdf-notes":true,"aktu-pyq":true,"cae":true,"handwritten":true,"quantum":true,"question-bank":true},"4th/KEE075":{"pdf-notes":true,"aktu-pyq":true,"cae":true,"handwritten":true,"quantum":true,"question-bank":true},"4th/KEE076":{"pdf-notes":true,"aktu-pyq":true,"cae":true,"handwritten":true,"quantum":true,"question-bank":true},"4th/KEE077":{"pdf-notes":true,"aktu-pyq":true,"cae":true,"handwritten":true,"quantum":true,"question-bank":true},"4th/KEE078":{"pdf-notes":true,"aktu-pyq":true,"cae":true,"handwritten":true,"quantum":true,"question-bank":true},"4th/KEE079":{"pdf-notes":true,"aktu-pyq":true,"cae":true,"handwritten":true,"quantum":true,"question-bank":true},"4th/KHU701":{"pdf-notes":true,"aktu-pyq":true,"cae":true,"handwritten":true,"quantum":true,"question-bank":true},"4th/KHU702":{"pdf-notes":true,"aktu-pyq":true,"cae":true,"handwritten":true,"quantum":true,"question-bank":true},"4th/KIT071":{"pdf-notes":true,"aktu-pyq":true,"cae":true,"handwritten":true,"quantum":true,"question-bank":true},"4th/KME071":{"pdf-notes":true,"aktu-pyq":true,"cae":true,"handwritten":true,"quantum":true,"question-bank":true},"4th/KME072":{"pdf-notes":true,"aktu-pyq":true,"cae":true,"handwritten":true,"quantum":true,"question-bank":true},"4th/KME073":{"pdf-notes":true,"aktu-pyq":true,"cae":true,"handwritten":true,"quantum":true,"question-bank":true},"4th/KME074":{"pdf-notes":true,"aktu-pyq":true,"cae":true,"handwritten":true,"quantum":true,"question-bank":true},"4th/KME075":{"pdf-notes":true,"aktu-pyq":true,"cae":true,"handwritten":true,"quantum":true,"question-bank":true},"4th/KME076":{"pdf-notes":true,"aktu-pyq":true,"cae":true,"handwritten":true,"quantum":true,"question-bank":true},"4th/KOE071":{"pdf-notes":true,"aktu-pyq":true,"cae":true,"handwritten":true,"quantum":true,"question-bank":true},"4th/KOE072":{"pdf-notes":true,"aktu-pyq":true,"cae":true,"handwritten":true,"quantum":true,"question-bank":true},"4th/KOE073":{"pdf-notes":true,"aktu-pyq":true,"cae":true,"handwritten":true,"quantum":true,"question-bank":true},"4th/KOE074":{"pdf-notes":true,"aktu-pyq":true,"cae":true,"handwritten":true,"quantum":true,"question-bank":true},"4th/KOE075":{"pdf-notes":true,"aktu-pyq":true,"cae":true,"handwritten":true,"quantum":true,"question-bank":true},"4th/KOE076":{"pdf-notes":true,"aktu-pyq":true,"cae":true,"handwritten":true,"quantum":true,"question-bank":true},"4th/KOE077":{"pdf-notes":true,"aktu-pyq":true,"cae":true,"handwritten":true,"quantum":true,"question-bank":true},"4th/KOE078":{"pdf-notes":true,"aktu-pyq":true,"cae":true,"handwritten":true,"quantum":true,"question-bank":true},"4th/KOE079":{"pdf-notes":true,"aktu-pyq":true,"cae":true,"handwritten":true,"quantum":true,"question-bank":true},"4th/KOT071":{"pdf-notes":true,"aktu-pyq":true,"cae":true,"handwritten":true,"quantum":true,"question-bank":true},"4th/KOT075":{"pdf-notes":true,"aktu-pyq":true,"cae":true,"handwritten":true,"quantum":true,"question-bank":true},"4th/KOT076":{"pdf-notes":true,"aktu-pyq":true,"cae":true,"handwritten":true,"quantum":true,"question-bank":true},"4th/KOT710":{"pdf-notes":true,"aktu-pyq":true,"cae":true,"handwritten":true,"quantum":true,"question-bank":true},"4th/KOT712":{"pdf-notes":true,"aktu-pyq":true,"cae":true,"handwritten":true,"quantum":true,"question-bank":true},"4th/KHU801":{"pdf-notes":true,"aktu-pyq":true,"cae":true,"handwritten":true,"quantum":true,"question-bank":true},"4th/KHU802":{"pdf-notes":true,"aktu-pyq":true,"cae":true,"handwritten":true,"quantum":true,"question-bank":true},"4th/KOE080":{"pdf-notes":true,"aktu-pyq":true,"cae":true,"handwritten":true,"quantum":true,"question-bank":true},"4th/KOE081":{"pdf-notes":true,"aktu-pyq":true,"cae":true,"handwritten":true,"quantum":true,"question-bank":true},"4th/KOE082":{"pdf-notes":true,"aktu-pyq":true,"cae":true,"handwritten":true,"quantum":true,"question-bank":true},"4th/KOE083":{"pdf-notes":true,"aktu-pyq":true,"cae":true,"handwritten":true,"quantum":true,"question-bank":true},"4th/KOE084":{"pdf-notes":true,"aktu-pyq":true,"cae":true,"handwritten":true,"quantum":true,"question-bank":true},"4th/KOE085":{"pdf-notes":true,"aktu-pyq":true,"cae":true,"handwritten":true,"quantum":true,"question-bank":true},"4th/KOE086":{"pdf-notes":true,"aktu-pyq":true,"cae":true,"handwritten":true,"quantum":true,"question-bank":true},"4th/KOE087":{"pdf-notes":true,"aktu-pyq":true,"cae":true,"handwritten":true,"quantum":true,"question-bank":true},"4th/KOE088":{"pdf-notes":true,"aktu-pyq":true,"cae":true,"handwritten":true,"quantum":true,"question-bank":true},"4th/KOE089":{"pdf-notes":true,"aktu-pyq":true,"cae":true,"handwritten":true,"quantum":true,"question-bank":true},"4th/KOE090":{"pdf-notes":true,"aktu-pyq":true,"cae":true,"handwritten":true,"quantum":true,"question-bank":true},"4th/KOE091":{"pdf-notes":true,"aktu-pyq":true,"cae":true,"handwritten":true,"quantum":true,"question-bank":true},"4th/KOE092":{"pdf-notes":true,"aktu-pyq":true,"cae":true,"handwritten":true,"quantum":true,"question-bank":true},"4th/KOE093":{"pdf-notes":true,"aktu-pyq":true,"cae":true,"handwritten":true,"quantum":true,"question-bank":true},"4th/KOE094":{"pdf-notes":true,"aktu-pyq":true,"cae":true,"handwritten":true,"quantum":true,"question-bank":true},"4th/KOE095":{"pdf-notes":true,"aktu-pyq":true,"cae":true,"handwritten":true,"quantum":true,"question-bank":true},"4th/KOE096":{"pdf-notes":true,"aktu-pyq":true,"cae":true,"handwritten":true,"quantum":true,"question-bank":true},"4th/KOE097":{"pdf-notes":true,"aktu-pyq":true,"cae":true,"handwritten":true,"quantum":true,"question-bank":true},"4th/KOE098":{"pdf-notes":true,"aktu-pyq":true,"cae":true,"handwritten":true,"quantum":true,"question-bank":true},"4th/KOE099":{"pdf-notes":true,"aktu-pyq":true,"cae":true,"handwritten":true,"quantum":true,"question-bank":true}}